{
   "results" : [
      {
         "address_components" : [
            {
               "long_name" : "5",
               "short_name" : "5",
               "types" : [ "street_number" ]
            },
            {
               "long_name" : "Via Vincenzo di Marco",
               "short_name" : "Via Vincenzo di Marco",
               "types" : [ "route" ]
            },
            {
               "long_name" : "Palermo",
               "short_name" : "Palermo",
               "types" : [ "locality", "political" ]
            },
            {
               "long_name" : "Palermo",
               "short_name" : "Palermo",
               "types" : [ "administrative_area_level_3", "political" ]
            },
            {
               "long_name" : "Palermo",
               "short_name" : "PA",
               "types" : [ "administrative_area_level_2", "political" ]
            },
            {
               "long_name" : "PA",
               "short_name" : "PA",
               "types" : [ "administrative_area_level_1", "political" ]
            },
            {
               "long_name" : "Italy",
               "short_name" : "IT",
               "types" : [ "country", "political" ]
            },
            {
               "long_name" : "90143",
               "short_name" : "90143",
               "types" : [ "postal_code" ]
            }
         ],
         "formatted_address" : "Via Vincenzo di Marco, 5, 90143 Palermo, Italy",
         "geometry" : {
            "location" : {
               "lat" : 38.1349816,
               "lng" : 13.3509238
            },
            "location_type" : "ROOFTOP",
            "viewport" : {
               "northeast" : {
                  "lat" : 38.13633058029149,
                  "lng" : 13.3522727802915
               },
               "southwest" : {
                  "lat" : 38.13363261970849,
                  "lng" : 13.3495748197085
               }
            }
         },
         "partial_match" : true,
         "types" : [ "street_address" ]
      }
   ],
   "status" : "OK"
}
